{
  "best_epoch": 61,
  "peak_worker_0_memory_MB": 2330.69921875,
  "peak_gpu_0_memory_MB": 65.09326171875,
  "training_duration": "0:00:19.573950",
  "training_start_epoch": 0,
  "training_epochs": 69,
  "epoch": 69,
  "training_accuracy": 0.9697892271662764,
  "training_loss": 0.17711931166808997,
  "training_worker_0_memory_MB": 2330.69921875,
  "training_gpu_0_memory_MB": 65.09326171875,
  "validation_accuracy": 0.8013245033112583,
  "validation_loss": 0.9112939953804016,
  "best_validation_accuracy": 0.7980132450331126,
  "best_validation_loss": 0.8867629706859589
}