{
  "best_epoch": 19,
  "peak_worker_0_memory_MB": 2330.69921875,
  "peak_gpu_0_memory_MB": 65.09326171875,
  "training_duration": "0:00:05.669374",
  "training_start_epoch": 0,
  "training_epochs": 19,
  "epoch": 19,
  "training_accuracy": 0.814519906323185,
  "training_loss": 1.1324777273989435,
  "training_worker_0_memory_MB": 2330.69921875,
  "training_gpu_0_memory_MB": 65.09326171875,
  "validation_accuracy": 0.7350993377483444,
  "validation_loss": 1.3642895102500916,
  "best_validation_accuracy": 0.7350993377483444,
  "best_validation_loss": 1.3642895102500916
}