{
  "best_epoch": 34,
  "peak_worker_0_memory_MB": 2319.48828125,
  "peak_gpu_0_memory_MB": 51.08984375,
  "training_duration": "0:00:09.850226",
  "training_start_epoch": 0,
  "training_epochs": 34,
  "epoch": 34,
  "training_accuracy": 0.9241217798594847,
  "training_loss": 0.4713148439108436,
  "training_worker_0_memory_MB": 2319.48828125,
  "training_gpu_0_memory_MB": 51.08984375,
  "validation_accuracy": 0.7847682119205298,
  "validation_loss": 0.9606286883354187,
  "best_validation_accuracy": 0.7847682119205298,
  "best_validation_loss": 0.9606286883354187
}