{
  "best_epoch": 25,
  "peak_worker_0_memory_MB": 2370.390625,
  "peak_gpu_0_memory_MB": 89.33056640625,
  "training_duration": "0:00:14.871408",
  "training_start_epoch": 0,
  "training_epochs": 29,
  "epoch": 29,
  "training_accuracy": 0.7916466634661545,
  "training_loss": 0.8995942109413729,
  "training_worker_0_memory_MB": 2370.390625,
  "training_gpu_0_memory_MB": 89.33056640625,
  "validation_accuracy": 0.7897350993377483,
  "validation_loss": 0.9469224750995636,
  "best_validation_accuracy": 0.7814569536423841,
  "best_validation_loss": 0.9305986881256103
}