{
  "best_epoch": 22,
  "peak_worker_0_memory_MB": 2328.3125,
  "peak_gpu_0_memory_MB": 64.7041015625,
  "training_duration": "0:00:05.582708",
  "training_start_epoch": 0,
  "training_epochs": 22,
  "epoch": 22,
  "training_accuracy": 0.9271958666040394,
  "training_loss": 0.46428884276703225,
  "training_worker_0_memory_MB": 2328.3125,
  "training_gpu_0_memory_MB": 64.7041015625,
  "validation_accuracy": 0.7814569536423841,
  "validation_loss": 0.9999631524085999,
  "best_validation_accuracy": 0.7814569536423841,
  "best_validation_loss": 0.9999631524085999
}