{
  "best_epoch": 0,
  "peak_worker_0_memory_MB": 2316.2890625,
  "peak_gpu_0_memory_MB": 62.47802734375,
  "training_duration": "0:00:00.267019",
  "training_start_epoch": 0,
  "training_epochs": 0,
  "epoch": 0,
  "training_accuracy": 0.13395784543325526,
  "training_loss": 3.9450008513322516,
  "training_worker_0_memory_MB": 2316.2890625,
  "training_gpu_0_memory_MB": 62.47802734375,
  "validation_accuracy": 0.19536423841059603,
  "validation_loss": 3.4998045682907106,
  "best_validation_accuracy": 0.19536423841059603,
  "best_validation_loss": 3.4998045682907106
}