{
  "best_epoch": 32,
  "peak_worker_0_memory_MB": 2327.01171875,
  "peak_gpu_0_memory_MB": 69.92529296875,
  "training_duration": "0:00:08.707108",
  "training_start_epoch": 0,
  "training_epochs": 32,
  "epoch": 32,
  "training_accuracy": 0.8664760228772548,
  "training_loss": 0.7931632763809628,
  "training_worker_0_memory_MB": 2327.01171875,
  "training_gpu_0_memory_MB": 69.92529296875,
  "validation_accuracy": 0.7715231788079471,
  "validation_loss": 1.0677476167678832,
  "best_validation_accuracy": 0.7715231788079471,
  "best_validation_loss": 1.0677476167678832
}