{
  "best_epoch": 5,
  "peak_worker_0_memory_MB": 2370.390625,
  "peak_gpu_0_memory_MB": 89.33056640625,
  "training_duration": "0:00:02.943951",
  "training_start_epoch": 0,
  "training_epochs": 5,
  "epoch": 5,
  "training_accuracy": 0.7562409985597696,
  "training_loss": 1.430873167878799,
  "training_worker_0_memory_MB": 2370.390625,
  "training_gpu_0_memory_MB": 89.33056640625,
  "validation_accuracy": 0.7417218543046358,
  "validation_loss": 1.2475627303123473,
  "best_validation_accuracy": 0.7417218543046358,
  "best_validation_loss": 1.2475627303123473
}