{
  "best_epoch": 0,
  "peak_worker_0_memory_MB": 2319.46875,
  "peak_gpu_0_memory_MB": 51.08984375,
  "training_duration": "0:00:00.252518",
  "training_start_epoch": 0,
  "training_epochs": 0,
  "epoch": 0,
  "training_accuracy": 0.18758782201405153,
  "training_loss": 4.029954009981298,
  "training_worker_0_memory_MB": 2319.46875,
  "training_gpu_0_memory_MB": 51.08984375,
  "validation_accuracy": 0.34271523178807944,
  "validation_loss": 3.7402956962585447,
  "best_validation_accuracy": 0.34271523178807944,
  "best_validation_loss": 3.7402956962585447
}