{
  "best_epoch": 18,
  "peak_worker_0_memory_MB": 2365.1484375,
  "peak_gpu_0_memory_MB": 84.50341796875,
  "training_duration": "0:00:11.654115",
  "training_start_epoch": 0,
  "training_epochs": 23,
  "epoch": 23,
  "training_accuracy": 0.9923187710033605,
  "training_loss": 0.07289187018652908,
  "training_worker_0_memory_MB": 2365.1484375,
  "training_gpu_0_memory_MB": 84.50341796875,
  "validation_accuracy": 0.8112582781456954,
  "validation_loss": 0.915789008140564,
  "best_validation_accuracy": 0.8029801324503312,
  "best_validation_loss": 0.8952507615089417
}