{
  "best_epoch": 12,
  "peak_worker_0_memory_MB": 2371.23046875,
  "peak_gpu_0_memory_MB": 89.33056640625,
  "training_duration": "0:00:06.101933",
  "training_start_epoch": 0,
  "training_epochs": 12,
  "epoch": 12,
  "training_accuracy": 0.714594335093615,
  "training_loss": 1.2423337998280999,
  "training_worker_0_memory_MB": 2371.23046875,
  "training_gpu_0_memory_MB": 89.33056640625,
  "validation_accuracy": 0.7731788079470199,
  "validation_loss": 1.0109801530838012,
  "best_validation_accuracy": 0.7731788079470199,
  "best_validation_loss": 1.0109801530838012
}