{
  "best_epoch": 54,
  "peak_worker_0_memory_MB": 2370.390625,
  "peak_gpu_0_memory_MB": 89.33056640625,
  "training_duration": "0:00:28.885509",
  "training_start_epoch": 0,
  "training_epochs": 59,
  "epoch": 59,
  "training_accuracy": 0.9768362938070091,
  "training_loss": 0.20514912209438005,
  "training_worker_0_memory_MB": 2370.390625,
  "training_gpu_0_memory_MB": 89.33056640625,
  "validation_accuracy": 0.7947019867549668,
  "validation_loss": 0.9063329041004181,
  "best_validation_accuracy": 0.7897350993377483,
  "best_validation_loss": 0.8972727000713349
}