{
  "best_epoch": 87,
  "peak_worker_0_memory_MB": 2313.4765625,
  "peak_gpu_0_memory_MB": 54.728515625,
  "training_duration": "0:00:18.255222",
  "training_start_epoch": 0,
  "training_epochs": 87,
  "epoch": 87,
  "training_accuracy": 0.81919577340769,
  "training_loss": 1.0220548035921875,
  "training_worker_0_memory_MB": 2313.4765625,
  "training_gpu_0_memory_MB": 54.728515625,
  "validation_accuracy": 0.7549668874172185,
  "validation_loss": 1.2174546003341675,
  "best_validation_accuracy": 0.7549668874172185,
  "best_validation_loss": 1.2174546003341675
}