{
  "best_epoch": 59,
  "peak_worker_0_memory_MB": 2313.4765625,
  "peak_gpu_0_memory_MB": 54.728515625,
  "training_duration": "0:00:12.445615",
  "training_start_epoch": 0,
  "training_epochs": 59,
  "epoch": 59,
  "training_accuracy": 0.7082477252714998,
  "training_loss": 1.5533840148537248,
  "training_worker_0_memory_MB": 2313.4765625,
  "training_gpu_0_memory_MB": 54.728515625,
  "validation_accuracy": 0.706953642384106,
  "validation_loss": 1.6068087697029114,
  "best_validation_accuracy": 0.706953642384106,
  "best_validation_loss": 1.6068087697029114
}