{
  "best_epoch": 22,
  "peak_worker_0_memory_MB": 2268.2578125,
  "peak_gpu_0_memory_MB": 8.71728515625,
  "training_duration": "0:00:03.075144",
  "training_start_epoch": 0,
  "training_epochs": 22,
  "epoch": 22,
  "training_accuracy": 0.907647304638529,
  "training_loss": 0.3840047109283899,
  "training_worker_0_memory_MB": 2268.2578125,
  "training_gpu_0_memory_MB": 8.71728515625,
  "validation_accuracy": 0.8311258278145696,
  "validation_loss": 0.8505685269832611,
  "best_validation_accuracy": 0.8311258278145696,
  "best_validation_loss": 0.8505685269832611
}