{
  "best_epoch": 55,
  "peak_worker_0_memory_MB": 2316.2890625,
  "peak_gpu_0_memory_MB": 62.47802734375,
  "training_duration": "0:00:14.810803",
  "training_start_epoch": 0,
  "training_epochs": 55,
  "epoch": 55,
  "training_accuracy": 0.9154566744730679,
  "training_loss": 0.4276801194272824,
  "training_worker_0_memory_MB": 2316.2890625,
  "training_gpu_0_memory_MB": 62.47802734375,
  "validation_accuracy": 0.8029801324503312,
  "validation_loss": 0.8831126809120178,
  "best_validation_accuracy": 0.8029801324503312,
  "best_validation_loss": 0.8831126809120178
}