{
  "best_epoch": 34,
  "peak_worker_0_memory_MB": 2318.171875,
  "peak_gpu_0_memory_MB": 55.18505859375,
  "training_duration": "0:00:09.717233",
  "training_start_epoch": 0,
  "training_epochs": 36,
  "epoch": 36,
  "training_accuracy": 0.9640676373884453,
  "training_loss": 0.21451338480657606,
  "training_worker_0_memory_MB": 2318.171875,
  "training_gpu_0_memory_MB": 55.18505859375,
  "validation_accuracy": 0.7996688741721855,
  "validation_loss": 0.9521806418895722,
  "best_validation_accuracy": 0.7963576158940397,
  "best_validation_loss": 0.9355206996202469
}