{
  "best_epoch": 5,
  "peak_worker_0_memory_MB": 2328.05859375,
  "peak_gpu_0_memory_MB": 64.7041015625,
  "training_duration": "0:00:02.500946",
  "training_start_epoch": 0,
  "training_epochs": 8,
  "epoch": 8,
  "training_accuracy": 0.9889619539689996,
  "training_loss": 0.06823278249088507,
  "training_worker_0_memory_MB": 2328.05859375,
  "training_gpu_0_memory_MB": 64.7041015625,
  "validation_accuracy": 0.8112582781456954,
  "validation_loss": 0.9847217112779617,
  "best_validation_accuracy": 0.804635761589404,
  "best_validation_loss": 0.9478959798812866
}