{
  "best_epoch": 87,
  "peak_worker_0_memory_MB": 0,
  "training_duration": "0:00:52.671446",
  "training_start_epoch": 0,
  "training_epochs": 87,
  "epoch": 87,
  "training_accuracy": 0.6,
  "training_loss": 2.118605039914449,
  "training_reg_loss": 0.0,
  "training_worker_0_memory_MB": 0.0,
  "validation_accuracy": 0.5483333333333333,
  "validation_loss": 2.404603964404056,
  "validation_reg_loss": 0.0,
  "best_validation_accuracy": 0.5483333333333333,
  "best_validation_loss": 2.404603964404056,
  "best_validation_reg_loss": 0.0
}