{
  "best_epoch": 48,
  "peak_worker_0_memory_MB": 2316.2890625,
  "peak_gpu_0_memory_MB": 62.47802734375,
  "training_duration": "0:00:14.101386",
  "training_start_epoch": 0,
  "training_epochs": 52,
  "epoch": 52,
  "training_accuracy": 0.9505854800936768,
  "training_loss": 0.2634297211223574,
  "training_worker_0_memory_MB": 2316.2890625,
  "training_gpu_0_memory_MB": 62.47802734375,
  "validation_accuracy": 0.8062913907284768,
  "validation_loss": 0.9095121383666992,
  "best_validation_accuracy": 0.804635761589404,
  "best_validation_loss": 0.8609976828098297
}