{
  "best_epoch": 25,
  "peak_worker_0_memory_MB": 2365.1484375,
  "peak_gpu_0_memory_MB": 89.33056640625,
  "training_duration": "0:00:13.198656",
  "training_start_epoch": 0,
  "training_epochs": 26,
  "epoch": 26,
  "training_accuracy": 0.9473115698511761,
  "training_loss": 0.38861789622607124,
  "training_worker_0_memory_MB": 2365.1484375,
  "training_gpu_0_memory_MB": 89.33056640625,
  "validation_accuracy": 0.7913907284768212,
  "validation_loss": 0.9170579254627228,
  "best_validation_accuracy": 0.7897350993377483,
  "best_validation_loss": 0.8961759716272354
}