{
  "best_epoch": 27,
  "peak_worker_0_memory_MB": 2328.3125,
  "peak_gpu_0_memory_MB": 64.7041015625,
  "training_duration": "0:00:06.990340",
  "training_start_epoch": 0,
  "training_epochs": 28,
  "epoch": 28,
  "training_accuracy": 0.2646782527007985,
  "training_loss": 3.1318741307329776,
  "training_worker_0_memory_MB": 2328.3125,
  "training_gpu_0_memory_MB": 64.7041015625,
  "validation_accuracy": 0.3741721854304636,
  "validation_loss": 3.0481969594955443,
  "best_validation_accuracy": 0.3658940397350993,
  "best_validation_loss": 3.0399447202682497
}