{
  "best_epoch": 68,
  "peak_worker_0_memory_MB": 2331.171875,
  "peak_gpu_0_memory_MB": 65.09326171875,
  "training_duration": "0:00:17.172928",
  "training_start_epoch": 0,
  "training_epochs": 69,
  "epoch": 69,
  "training_accuracy": 0.8754098360655738,
  "training_loss": 0.6635862410958133,
  "training_worker_0_memory_MB": 2331.171875,
  "training_gpu_0_memory_MB": 65.09326171875,
  "validation_accuracy": 0.7947019867549668,
  "validation_loss": 0.9939730346202851,
  "best_validation_accuracy": 0.793046357615894,
  "best_validation_loss": 0.9779494941234589
}