{
  "best_epoch": 11,
  "peak_worker_0_memory_MB": 2283.93359375,
  "peak_gpu_0_memory_MB": 29.619140625,
  "training_duration": "0:00:01.930609",
  "training_start_epoch": 0,
  "training_epochs": 11,
  "epoch": 11,
  "training_accuracy": 0.9017969076473047,
  "training_loss": 0.47735504178624405,
  "training_worker_0_memory_MB": 2283.93359375,
  "training_gpu_0_memory_MB": 29.619140625,
  "validation_accuracy": 0.7864238410596026,
  "validation_loss": 0.9348385572433472,
  "best_validation_accuracy": 0.7864238410596026,
  "best_validation_loss": 0.9348385572433472
}