{
  "best_epoch": 21,
  "peak_worker_0_memory_MB": 2317.36328125,
  "peak_gpu_0_memory_MB": 51.4853515625,
  "training_duration": "0:00:06.349771",
  "training_start_epoch": 0,
  "training_epochs": 21,
  "epoch": 21,
  "training_accuracy": 0.7629976580796253,
  "training_loss": 1.3885429279128116,
  "training_worker_0_memory_MB": 2317.36328125,
  "training_gpu_0_memory_MB": 51.4853515625,
  "validation_accuracy": 0.7201986754966887,
  "validation_loss": 1.5402682423591614,
  "best_validation_accuracy": 0.7201986754966887,
  "best_validation_loss": 1.5402682423591614
}