{
  "best_epoch": 61,
  "peak_worker_0_memory_MB": 2320.41015625,
  "peak_gpu_0_memory_MB": 54.71142578125,
  "training_duration": "0:00:16.032786",
  "training_start_epoch": 0,
  "training_epochs": 62,
  "epoch": 62,
  "training_accuracy": 0.7257611241217798,
  "training_loss": 1.0828336352732644,
  "training_worker_0_memory_MB": 2320.41015625,
  "training_gpu_0_memory_MB": 54.71142578125,
  "validation_accuracy": 0.7897350993377483,
  "validation_loss": 0.9235769808292389,
  "best_validation_accuracy": 0.7880794701986755,
  "best_validation_loss": 0.9122388780117034
}