{
  "best_epoch": 46,
  "peak_worker_0_memory_MB": 2298.41015625,
  "peak_gpu_0_memory_MB": 50.91064453125,
  "training_duration": "0:00:32.075075",
  "training_start_epoch": 0,
  "training_epochs": 46,
  "epoch": 46,
  "training_accuracy": 0.45507730881738406,
  "training_loss": 2.100801103993466,
  "training_worker_0_memory_MB": 2298.41015625,
  "training_gpu_0_memory_MB": 50.91064453125,
  "validation_accuracy": 0.6473509933774835,
  "validation_loss": 1.5627191662788391,
  "best_validation_accuracy": 0.6473509933774835,
  "best_validation_loss": 1.5627191662788391
}