{
  "best_epoch": 1,
  "peak_worker_0_memory_MB": 2298.41015625,
  "peak_gpu_0_memory_MB": 50.91064453125,
  "training_duration": "0:00:01.367946",
  "training_start_epoch": 0,
  "training_epochs": 1,
  "epoch": 1,
  "training_accuracy": 0.18470539072294193,
  "training_loss": 3.332721515705711,
  "training_worker_0_memory_MB": 2298.41015625,
  "training_gpu_0_memory_MB": 50.91064453125,
  "validation_accuracy": 0.326158940397351,
  "validation_loss": 2.829737687110901,
  "best_validation_accuracy": 0.326158940397351,
  "best_validation_loss": 2.829737687110901
}