{
  "best_epoch": 16,
  "peak_worker_0_memory_MB": 2311.37890625,
  "peak_gpu_0_memory_MB": 43.572265625,
  "training_duration": "0:00:04.023633",
  "training_start_epoch": 0,
  "training_epochs": 16,
  "epoch": 16,
  "training_accuracy": 0.5217798594847776,
  "training_loss": 2.4680744000335237,
  "training_worker_0_memory_MB": 2311.37890625,
  "training_gpu_0_memory_MB": 43.572265625,
  "validation_accuracy": 0.5496688741721855,
  "validation_loss": 2.4177414774894714,
  "best_validation_accuracy": 0.5496688741721855,
  "best_validation_loss": 2.4177414774894714
}