{
  "best_epoch": 12,
  "peak_worker_0_memory_MB": 2331.171875,
  "peak_gpu_0_memory_MB": 65.09326171875,
  "training_duration": "0:00:03.317279",
  "training_start_epoch": 0,
  "training_epochs": 12,
  "epoch": 12,
  "training_accuracy": 0.8932084309133489,
  "training_loss": 0.6454106627115562,
  "training_worker_0_memory_MB": 2331.171875,
  "training_gpu_0_memory_MB": 65.09326171875,
  "validation_accuracy": 0.7764900662251656,
  "validation_loss": 1.0239199459552766,
  "best_validation_accuracy": 0.7764900662251656,
  "best_validation_loss": 1.0239199459552766
}