{
  "best_epoch": 0,
  "peak_worker_0_memory_MB": 0,
  "training_duration": "0:00:00.674721",
  "training_start_epoch": 0,
  "training_epochs": 0,
  "epoch": 0,
  "training_accuracy": 0.30083333333333334,
  "training_loss": 3.840634002685547,
  "training_reg_loss": 0.0,
  "training_worker_0_memory_MB": 0.0,
  "validation_accuracy": 0.4716666666666667,
  "validation_loss": 3.204745832242464,
  "validation_reg_loss": 0.0,
  "best_validation_accuracy": 0.4716666666666667,
  "best_validation_loss": 3.204745832242464,
  "best_validation_reg_loss": 0.0
}