{
  "best_epoch": 16,
  "peak_worker_0_memory_MB": 2319.734375,
  "peak_gpu_0_memory_MB": 51.08984375,
  "training_duration": "0:00:04.879649",
  "training_start_epoch": 0,
  "training_epochs": 17,
  "epoch": 17,
  "training_accuracy": 0.9620608899297424,
  "training_loss": 0.26208651377193964,
  "training_worker_0_memory_MB": 2319.734375,
  "training_gpu_0_memory_MB": 51.08984375,
  "validation_accuracy": 0.7864238410596026,
  "validation_loss": 0.9408515512943267,
  "best_validation_accuracy": 0.7880794701986755,
  "best_validation_loss": 0.897587850689888
}