{
  "best_epoch": 67,
  "peak_worker_0_memory_MB": 2313.5546875,
  "peak_gpu_0_memory_MB": 54.728515625,
  "training_duration": "0:00:14.508266",
  "training_start_epoch": 0,
  "training_epochs": 67,
  "epoch": 67,
  "training_accuracy": 0.9301438215438802,
  "training_loss": 0.4089900387658013,
  "training_worker_0_memory_MB": 2313.5546875,
  "training_gpu_0_memory_MB": 54.728515625,
  "validation_accuracy": 0.7897350993377483,
  "validation_loss": 0.9596604883670807,
  "best_validation_accuracy": 0.7897350993377483,
  "best_validation_loss": 0.9596604883670807
}