{
  "best_epoch": 91,
  "peak_worker_0_memory_MB": 2331.171875,
  "peak_gpu_0_memory_MB": 65.09326171875,
  "training_duration": "0:00:23.913894",
  "training_start_epoch": 0,
  "training_epochs": 93,
  "epoch": 93,
  "training_accuracy": 0.33747072599531613,
  "training_loss": 2.5450832132083265,
  "training_worker_0_memory_MB": 2331.171875,
  "training_gpu_0_memory_MB": 65.09326171875,
  "validation_accuracy": 0.6688741721854304,
  "validation_loss": 1.7638376355171204,
  "best_validation_accuracy": 0.6639072847682119,
  "best_validation_loss": 1.756879949569702
}