{
  "best_epoch": 23,
  "peak_worker_0_memory_MB": 2328.29296875,
  "peak_gpu_0_memory_MB": 64.7041015625,
  "training_duration": "0:00:06.777479",
  "training_start_epoch": 0,
  "training_epochs": 24,
  "epoch": 24,
  "training_accuracy": 0.9783936120244247,
  "training_loss": 0.1282704522583022,
  "training_worker_0_memory_MB": 2328.29296875,
  "training_gpu_0_memory_MB": 64.7041015625,
  "validation_accuracy": 0.8062913907284768,
  "validation_loss": 0.9468255043029785,
  "best_validation_accuracy": 0.8062913907284768,
  "best_validation_loss": 0.9163367092609406
}