{
  "best_epoch": 61,
  "peak_worker_0_memory_MB": 2330.9140625,
  "peak_gpu_0_memory_MB": 65.09326171875,
  "training_duration": "0:00:17.911775",
  "training_start_epoch": 0,
  "training_epochs": 62,
  "epoch": 62,
  "training_accuracy": 0.9695550351288056,
  "training_loss": 0.18229386088118624,
  "training_worker_0_memory_MB": 2330.9140625,
  "training_gpu_0_memory_MB": 65.09326171875,
  "validation_accuracy": 0.8029801324503312,
  "validation_loss": 0.8840579092502594,
  "best_validation_accuracy": 0.8013245033112583,
  "best_validation_loss": 0.876393586397171
}