{
  "best_epoch": 14,
  "peak_worker_0_memory_MB": 2327.01171875,
  "peak_gpu_0_memory_MB": 69.92529296875,
  "training_duration": "0:00:04.187451",
  "training_start_epoch": 0,
  "training_epochs": 14,
  "epoch": 14,
  "training_accuracy": 0.6207655081390233,
  "training_loss": 2.036144572827551,
  "training_worker_0_memory_MB": 2327.01171875,
  "training_gpu_0_memory_MB": 69.92529296875,
  "validation_accuracy": 0.6208609271523179,
  "validation_loss": 1.9941012144088746,
  "best_validation_accuracy": 0.6208609271523179,
  "best_validation_loss": 1.9941012144088746
}