{
  "best_epoch": 6,
  "peak_worker_0_memory_MB": 2271.57421875,
  "peak_gpu_0_memory_MB": 15.515625,
  "training_duration": "0:00:00.571462",
  "training_start_epoch": 0,
  "training_epochs": 6,
  "epoch": 6,
  "training_accuracy": 0.7062600321027287,
  "training_loss": 1.806810438632965,
  "training_worker_0_memory_MB": 2271.57421875,
  "training_gpu_0_memory_MB": 15.515625,
  "validation_accuracy": 0.7715231788079471,
  "validation_loss": 1.760185968875885,
  "best_validation_accuracy": 0.7715231788079471,
  "best_validation_loss": 1.760185968875885
}