{
  "best_epoch": 1,
  "peak_worker_0_memory_MB": 2308.46484375,
  "peak_gpu_0_memory_MB": 54.28173828125,
  "training_duration": "0:00:00.495934",
  "training_start_epoch": 0,
  "training_epochs": 1,
  "epoch": 1,
  "training_accuracy": 0.11451990632318501,
  "training_loss": 3.7892937090859484,
  "training_worker_0_memory_MB": 2308.46484375,
  "training_gpu_0_memory_MB": 54.28173828125,
  "validation_accuracy": 0.271523178807947,
  "validation_loss": 3.428962302207947,
  "best_validation_accuracy": 0.271523178807947,
  "best_validation_loss": 3.428962302207947
}