{
  "best_epoch": 8,
  "peak_worker_0_memory_MB": 2308.46484375,
  "peak_gpu_0_memory_MB": 54.28173828125,
  "training_duration": "0:00:02.297274",
  "training_start_epoch": 0,
  "training_epochs": 8,
  "epoch": 8,
  "training_accuracy": 0.30304449648711945,
  "training_loss": 2.921946198192995,
  "training_worker_0_memory_MB": 2308.46484375,
  "training_gpu_0_memory_MB": 54.28173828125,
  "validation_accuracy": 0.5198675496688742,
  "validation_loss": 2.520446300506592,
  "best_validation_accuracy": 0.5198675496688742,
  "best_validation_loss": 2.520446300506592
}