{
  "best_epoch": 12,
  "peak_worker_0_memory_MB": 2327.01171875,
  "peak_gpu_0_memory_MB": 69.92529296875,
  "training_duration": "0:00:03.461413",
  "training_start_epoch": 0,
  "training_epochs": 12,
  "epoch": 12,
  "training_accuracy": 0.6700395952485702,
  "training_loss": 1.637080916100078,
  "training_worker_0_memory_MB": 2327.01171875,
  "training_gpu_0_memory_MB": 69.92529296875,
  "validation_accuracy": 0.7036423841059603,
  "validation_loss": 1.5431732654571533,
  "best_validation_accuracy": 0.7036423841059603,
  "best_validation_loss": 1.5431732654571533
}