{
  "best_epoch": 11,
  "peak_worker_0_memory_MB": 2293.890625,
  "peak_gpu_0_memory_MB": 48.38671875,
  "training_duration": "0:00:08.976930",
  "training_start_epoch": 0,
  "training_epochs": 13,
  "epoch": 13,
  "training_accuracy": 0.7012118679481822,
  "training_loss": 1.3465615965818103,
  "training_worker_0_memory_MB": 2293.890625,
  "training_gpu_0_memory_MB": 48.38671875,
  "validation_accuracy": 0.7947019867549668,
  "validation_loss": 1.0637374222278595,
  "best_validation_accuracy": 0.7947019867549668,
  "best_validation_loss": 1.0173373460769652
}