{
  "best_epoch": 2,
  "peak_worker_0_memory_MB": 2308.46484375,
  "peak_gpu_0_memory_MB": 54.28173828125,
  "training_duration": "0:00:00.756812",
  "training_start_epoch": 0,
  "training_epochs": 2,
  "epoch": 2,
  "training_accuracy": 0.7199063231850117,
  "training_loss": 1.2117254324813387,
  "training_worker_0_memory_MB": 2308.46484375,
  "training_gpu_0_memory_MB": 54.28173828125,
  "validation_accuracy": 0.7847682119205298,
  "validation_loss": 0.9605600297451019,
  "best_validation_accuracy": 0.7847682119205298,
  "best_validation_loss": 0.9605600297451019
}