{
  "best_epoch": 24,
  "peak_worker_0_memory_MB": 2328.6875,
  "peak_gpu_0_memory_MB": 61.63037109375,
  "training_duration": "0:00:06.760386",
  "training_start_epoch": 0,
  "training_epochs": 24,
  "epoch": 24,
  "training_accuracy": 0.9046838407494145,
  "training_loss": 0.6496306288598189,
  "training_worker_0_memory_MB": 2328.6875,
  "training_gpu_0_memory_MB": 61.63037109375,
  "validation_accuracy": 0.7731788079470199,
  "validation_loss": 1.1224481225013734,
  "best_validation_accuracy": 0.7731788079470199,
  "best_validation_loss": 1.1224481225013734
}