{
  "best_epoch": 97,
  "peak_worker_0_memory_MB": 2320.6953125,
  "peak_gpu_0_memory_MB": 54.71142578125,
  "training_duration": "0:00:26.197157",
  "training_start_epoch": 0,
  "training_epochs": 98,
  "epoch": 98,
  "training_accuracy": 0.9463700234192037,
  "training_loss": 0.32798542838488054,
  "training_worker_0_memory_MB": 2320.6953125,
  "training_gpu_0_memory_MB": 54.71142578125,
  "validation_accuracy": 0.7880794701986755,
  "validation_loss": 0.9413602411746979,
  "best_validation_accuracy": 0.7880794701986755,
  "best_validation_loss": 0.9130965232849121
}