{
  "best_epoch": 45,
  "peak_worker_0_memory_MB": 2316.03515625,
  "peak_gpu_0_memory_MB": 62.47802734375,
  "training_duration": "0:00:13.598459",
  "training_start_epoch": 0,
  "training_epochs": 46,
  "epoch": 46,
  "training_accuracy": 0.9285714285714286,
  "training_loss": 0.47507631645273807,
  "training_worker_0_memory_MB": 2316.03515625,
  "training_gpu_0_memory_MB": 62.47802734375,
  "validation_accuracy": 0.7831125827814569,
  "validation_loss": 1.0027779936790466,
  "best_validation_accuracy": 0.7831125827814569,
  "best_validation_loss": 0.9983619451522827
}