{
  "best_epoch": 19,
  "peak_worker_0_memory_MB": 2269.83203125,
  "peak_gpu_0_memory_MB": 15.515625,
  "training_duration": "0:00:01.642677",
  "training_start_epoch": 0,
  "training_epochs": 19,
  "epoch": 19,
  "training_accuracy": 0.833868378812199,
  "training_loss": 0.9779316127300263,
  "training_worker_0_memory_MB": 2269.83203125,
  "training_gpu_0_memory_MB": 15.515625,
  "validation_accuracy": 0.8062913907284768,
  "validation_loss": 1.303589540719986,
  "best_validation_accuracy": 0.8062913907284768,
  "best_validation_loss": 1.303589540719986
}