{
  "best_epoch": 17,
  "peak_worker_0_memory_MB": 2313.5546875,
  "peak_gpu_0_memory_MB": 54.728515625,
  "training_duration": "0:00:03.734934",
  "training_start_epoch": 0,
  "training_epochs": 17,
  "epoch": 17,
  "training_accuracy": 0.9181097739947167,
  "training_loss": 0.4862589091062546,
  "training_worker_0_memory_MB": 2313.5546875,
  "training_gpu_0_memory_MB": 54.728515625,
  "validation_accuracy": 0.7864238410596026,
  "validation_loss": 0.9991480112075806,
  "best_validation_accuracy": 0.7864238410596026,
  "best_validation_loss": 0.9991480112075806
}