{
  "best_epoch": 2,
  "peak_worker_0_memory_MB": 2326.80078125,
  "peak_gpu_0_memory_MB": 69.92529296875,
  "training_duration": "0:00:00.822816",
  "training_start_epoch": 0,
  "training_epochs": 2,
  "epoch": 2,
  "training_accuracy": 0.21821381434227893,
  "training_loss": 3.236843400531345,
  "training_worker_0_memory_MB": 2326.80078125,
  "training_gpu_0_memory_MB": 69.92529296875,
  "validation_accuracy": 0.3228476821192053,
  "validation_loss": 3.1126572370529173,
  "best_validation_accuracy": 0.3228476821192053,
  "best_validation_loss": 3.1126572370529173
}