{
  "best_epoch": 23,
  "peak_worker_0_memory_MB": 2319.734375,
  "peak_gpu_0_memory_MB": 51.08984375,
  "training_duration": "0:00:05.917982",
  "training_start_epoch": 0,
  "training_epochs": 23,
  "epoch": 23,
  "training_accuracy": 0.6330210772833723,
  "training_loss": 1.7062951006106477,
  "training_worker_0_memory_MB": 2319.734375,
  "training_gpu_0_memory_MB": 51.08984375,
  "validation_accuracy": 0.706953642384106,
  "validation_loss": 1.5104058384895325,
  "best_validation_accuracy": 0.706953642384106,
  "best_validation_loss": 1.5104058384895325
}