{
  "best_epoch": 37,
  "peak_worker_0_memory_MB": 2370.390625,
  "peak_gpu_0_memory_MB": 89.33056640625,
  "training_duration": "0:00:19.518974",
  "training_start_epoch": 0,
  "training_epochs": 38,
  "epoch": 38,
  "training_accuracy": 0.906745079212674,
  "training_loss": 0.6523837956763406,
  "training_worker_0_memory_MB": 2370.390625,
  "training_gpu_0_memory_MB": 89.33056640625,
  "validation_accuracy": 0.7748344370860927,
  "validation_loss": 0.994360476732254,
  "best_validation_accuracy": 0.7731788079470199,
  "best_validation_loss": 0.9942478835582733
}