{
  "best_epoch": 2,
  "peak_worker_0_memory_MB": 2269.83203125,
  "peak_gpu_0_memory_MB": 15.515625,
  "training_duration": "0:00:00.261590",
  "training_start_epoch": 0,
  "training_epochs": 2,
  "epoch": 2,
  "training_accuracy": 0.1565008025682183,
  "training_loss": 3.785493993759155,
  "training_worker_0_memory_MB": 2269.83203125,
  "training_gpu_0_memory_MB": 15.515625,
  "validation_accuracy": 0.326158940397351,
  "validation_loss": 3.594137978553772,
  "best_validation_accuracy": 0.326158940397351,
  "best_validation_loss": 3.594137978553772
}