{
  "best_epoch": 10,
  "peak_worker_0_memory_MB": 2284.25,
  "peak_gpu_0_memory_MB": 49.984375,
  "training_duration": "0:00:08.652678",
  "training_start_epoch": 0,
  "training_epochs": 12,
  "epoch": 12,
  "training_accuracy": 0.8537400752193899,
  "training_loss": 0.6269801470794176,
  "training_worker_0_memory_MB": 2284.25,
  "training_gpu_0_memory_MB": 49.984375,
  "validation_accuracy": 0.7814569536423841,
  "validation_loss": 1.1689591586589814,
  "best_validation_accuracy": 0.7748344370860927,
  "best_validation_loss": 1.1106995522975922
}