{
  "best_epoch": 15,
  "peak_worker_0_memory_MB": 2270.7265625,
  "peak_gpu_0_memory_MB": 8.73193359375,
  "training_duration": "0:00:02.341690",
  "training_start_epoch": 0,
  "training_epochs": 16,
  "epoch": 16,
  "training_accuracy": 0.9084830756372754,
  "training_loss": 0.3752327824109479,
  "training_worker_0_memory_MB": 2270.7265625,
  "training_gpu_0_memory_MB": 8.73193359375,
  "validation_accuracy": 0.8278145695364238,
  "validation_loss": 0.87980877161026,
  "best_validation_accuracy": 0.8294701986754967,
  "best_validation_loss": 0.8518415987491608
}