{
  "best_epoch": 71,
  "peak_worker_0_memory_MB": 2326.74609375,
  "peak_gpu_0_memory_MB": 69.92529296875,
  "training_duration": "0:00:20.259310",
  "training_start_epoch": 0,
  "training_epochs": 76,
  "epoch": 76,
  "training_accuracy": 0.9819621645402552,
  "training_loss": 0.10241001641326067,
  "training_worker_0_memory_MB": 2326.74609375,
  "training_gpu_0_memory_MB": 69.92529296875,
  "validation_accuracy": 0.804635761589404,
  "validation_loss": 0.9012477457523346,
  "best_validation_accuracy": 0.8062913907284768,
  "best_validation_loss": 0.8539419561624527
}