{
  "best_epoch": 27,
  "peak_worker_0_memory_MB": 2316.54296875,
  "peak_gpu_0_memory_MB": 51.12255859375,
  "training_duration": "0:00:23.086845",
  "training_start_epoch": 0,
  "training_epochs": 34,
  "epoch": 34,
  "training_accuracy": 0.8374425407438362,
  "training_loss": 0.6310582247219587,
  "training_worker_0_memory_MB": 2316.54296875,
  "training_gpu_0_memory_MB": 51.12255859375,
  "validation_accuracy": 0.8029801324503312,
  "validation_loss": 1.0305833578109742,
  "best_validation_accuracy": 0.7847682119205298,
  "best_validation_loss": 0.9352174244821072
}