{
  "best_epoch": 44,
  "peak_worker_0_memory_MB": 2313.53515625,
  "peak_gpu_0_memory_MB": 54.728515625,
  "training_duration": "0:00:09.895710",
  "training_start_epoch": 0,
  "training_epochs": 45,
  "epoch": 45,
  "training_accuracy": 0.9289697681244496,
  "training_loss": 0.4090111313594712,
  "training_worker_0_memory_MB": 2313.53515625,
  "training_gpu_0_memory_MB": 54.728515625,
  "validation_accuracy": 0.7880794701986755,
  "validation_loss": 0.9901049077510834,
  "best_validation_accuracy": 0.7897350993377483,
  "best_validation_loss": 0.9504498422145844
}