{
  "best_epoch": 32,
  "peak_worker_0_memory_MB": 2269.83203125,
  "peak_gpu_0_memory_MB": 15.515625,
  "training_duration": "0:00:02.665771",
  "training_start_epoch": 0,
  "training_epochs": 32,
  "epoch": 32,
  "training_accuracy": 0.8731942215088283,
  "training_loss": 0.5918965548276901,
  "training_worker_0_memory_MB": 2269.83203125,
  "training_gpu_0_memory_MB": 15.515625,
  "validation_accuracy": 0.8178807947019867,
  "validation_loss": 1.1285890638828278,
  "best_validation_accuracy": 0.8178807947019867,
  "best_validation_loss": 1.1285890638828278
}