{
  "best_epoch": 26,
  "peak_worker_0_memory_MB": 2317.36328125,
  "peak_gpu_0_memory_MB": 51.4853515625,
  "training_duration": "0:00:08.841892",
  "training_start_epoch": 0,
  "training_epochs": 34,
  "epoch": 34,
  "training_accuracy": 0.9925058548009368,
  "training_loss": 0.049983997426148674,
  "training_worker_0_memory_MB": 2317.36328125,
  "training_gpu_0_memory_MB": 51.4853515625,
  "validation_accuracy": 0.8013245033112583,
  "validation_loss": 0.94911630153656,
  "best_validation_accuracy": 0.8029801324503312,
  "best_validation_loss": 0.9013046890497207
}